Metadata-Version: 2.1
Name: webcorpus
Version: 0.2
Summary: Generate large textual corpora for almost any language by crawling the web
Home-page: https://github.com/divkakwani/webcorpus
Author: Divyanshu Kakwani
Author-email: divkakwani@gmail.com
License: UNKNOWN
Project-URL: Bug Reports, https://github.com/divkakwani/webcorpus/issues
Project-URL: Source, https://github.com/divkakwani/webcorpus
Keywords: dataset corpus
Platform: UNKNOWN
Classifier: Development Status :: 4 - Beta
Classifier: Intended Audience :: Developers
Classifier: License :: OSI Approved :: GNU General Public License v3 or later (GPLv3+)
Classifier: Programming Language :: Python :: 3
Classifier: Programming Language :: Python :: 3.5
Classifier: Programming Language :: Python :: 3.6
Classifier: Programming Language :: Python :: 3.7
Requires-Python: >=3.5
Requires-Dist: morfessor
Requires-Dist: boilerpipe3
Requires-Dist: tldextract
Requires-Dist: click
Requires-Dist: scrapy
Requires-Dist: tqdm
Requires-Dist: pandas
Requires-Dist: scrapyd
Requires-Dist: nltk
Requires-Dist: scrapyd-client
Requires-Dist: htmldate
